{
    "cols": [
        {
            "label": "Hora",
            "type": "date"
        },
        {
            "label": "Entrantes",
            "type": "number"
        },
        {
            "label": "Salientes",
            "type": "number"
        }
    ],
    "rows": [
        {
            "c": [
                {
                    "v": "Date(2020,0,23,0,30,0)"
                },
                {
                    "v": 57
                },
                {
                    "v": 48
                }
            ]
        },
        {
            "c": [
                {
                    "v": "Date(2020,0,23,1,0,0)"
                },
                {
                    "v": 85
                },
                {
                    "v": 75
                }
            ]
        },
        {
            "c": [
                {
                    "v": "Date(2020,0,23,1,30,0)"
                },
                {
                    "v": 86
                },
                {
                    "v": 70
                }
            ]
        },
        {
            "c": [
                {
                    "v": "Date(2020,0,23,2,0,0)"
                },
                {
                    "v": 70
                },
                {
                    "v": 99
                }
            ]
        },
        {
            "c": [
                {
                    "v": "Date(2020,0,23,2,30,0)"
                },
                {
                    "v": 87
                },
                {
                    "v": 61
                }
            ]
        },
        {
            "c": [
                {
                    "v": "Date(2020,0,23,3,0,0)"
                },
                {
                    "v": 81
                },
                {
                    "v": 82
                }
            ]
        },
        {
            "c": [
                {
                    "v": "Date(2020,0,23,3,30,0)"
                },
                {
                    "v": 95
                },
                {
                    "v": 73
                }
            ]
        },
        {
            "c": [
                {
                    "v": "Date(2020,0,23,4,0,0)"
                },
                {
                    "v": 86
                },
                {
                    "v": 78
                }
            ]
        },
        {
            "c": [
                {
                    "v": "Date(2020,0,23,4,30,0)"
                },
                {
                    "v": 70
                },
                {
                    "v": 86
                }
            ]
        },
        {
            "c": [
                {
                    "v": "Date(2020,0,23,5,0,0)"
                },
                {
                    "v": 67
                },
                {
                    "v": 62
                }
            ]
        },
        {
            "c": [
                {
                    "v": "Date(2020,0,23,5,30,0)"
                },
                {
                    "v": 63
                },
                {
                    "v": 69
                }
            ]
        },
        {
            "c": [
                {
                    "v": "Date(2020,0,23,6,0,0)"
                },
                {
                    "v": 75
                },
                {
                    "v": 98
                }
            ]
        },
        {
            "c": [
                {
                    "v": "Date(2020,0,23,6,30,0)"
                },
                {
                    "v": 63
                },
                {
                    "v": 85
                }
            ]
        },
        {
            "c": [
                {
                    "v": "Date(2020,0,23,7,0,0)"
                },
                {
                    "v": 68
                },
                {
                    "v": 77
                }
            ]
        },
        {
            "c": [
                {
                    "v": "Date(2020,0,23,7,30,0)"
                },
                {
                    "v": 94
                },
                {
                    "v": 77
                }
            ]
        },
        {
            "c": [
                {
                    "v": "Date(2020,0,23,8,0,0)"
                },
                {
                    "v": 86
                },
                {
                    "v": 60
                }
            ]
        },
        {
            "c": [
                {
                    "v": "Date(2020,0,23,8,30,0)"
                },
                {
                    "v": 59
                },
                {
                    "v": 66
                }
            ]
        },
        {
            "c": [
                {
                    "v": "Date(2020,0,23,9,0,0)"
                },
                {
                    "v": 73
                },
                {
                    "v": 89
                }
            ]
        },
        {
            "c": [
                {
                    "v": "Date(2020,0,23,9,30,0)"
                },
                {
                    "v": 76
                },
                {
                    "v": 77
                }
            ]
        },
        {
            "c": [
                {
                    "v": "Date(2020,0,23,10,0,0)"
                },
                {
                    "v": 64
                },
                {
                    "v": 64
                }
            ]
        },
        {
            "c": [
                {
                    "v": "Date(2020,0,23,10,30,0)"
                },
                {
                    "v": 66
                },
                {
                    "v": 70
                }
            ]
        },
        {
            "c": [
                {
                    "v": "Date(2020,0,23,11,0,0)"
                },
                {
                    "v": 109
                },
                {
                    "v": 62
                }
            ]
        },
        {
            "c": [
                {
                    "v": "Date(2020,0,23,11,30,0)"
                },
                {
                    "v": 57
                },
                {
                    "v": 67
                }
            ]
        },
        {
            "c": [
                {
                    "v": "Date(2020,0,23,12,0,0)"
                },
                {
                    "v": 70
                },
                {
                    "v": 90
                }
            ]
        },
        {
            "c": [
                {
                    "v": "Date(2020,0,23,12,30,0)"
                },
                {
                    "v": 66
                },
                {
                    "v": 73
                }
            ]
        },
        {
            "c": [
                {
                    "v": "Date(2020,0,23,13,0,0)"
                },
                {
                    "v": 79
                },
                {
                    "v": 89
                }
            ]
        },
        {
            "c": [
                {
                    "v": "Date(2020,0,23,13,30,0)"
                },
                {
                    "v": 70
                },
                {
                    "v": 74
                }
            ]
        },
        {
            "c": [
                {
                    "v": "Date(2020,0,23,14,0,0)"
                },
                {
                    "v": 63
                },
                {
                    "v": 57
                }
            ]
        },
        {
            "c": [
                {
                    "v": "Date(2020,0,23,14,30,0)"
                },
                {
                    "v": 89
                },
                {
                    "v": 80
                }
            ]
        },
        {
            "c": [
                {
                    "v": "Date(2020,0,23,15,0,0)"
                },
                {
                    "v": 87
                },
                {
                    "v": 71
                }
            ]
        },
        {
            "c": [
                {
                    "v": "Date(2020,0,23,15,30,0)"
                },
                {
                    "v": 52
                },
                {
                    "v": 75
                }
            ]
        },
        {
            "c": [
                {
                    "v": "Date(2020,0,23,16,0,0)"
                },
                {
                    "v": 72
                },
                {
                    "v": 83
                }
            ]
        },
        {
            "c": [
                {
                    "v": "Date(2020,0,23,16,30,0)"
                },
                {
                    "v": 90
                },
                {
                    "v": 57
                }
            ]
        },
        {
            "c": [
                {
                    "v": "Date(2020,0,23,17,0,0)"
                },
                {
                    "v": 82
                },
                {
                    "v": 76
                }
            ]
        },
        {
            "c": [
                {
                    "v": "Date(2020,0,23,17,30,0)"
                },
                {
                    "v": 65
                },
                {
                    "v": 75
                }
            ]
        },
        {
            "c": [
                {
                    "v": "Date(2020,0,23,18,0,0)"
                },
                {
                    "v": 84
                },
                {
                    "v": 55
                }
            ]
        },
        {
            "c": [
                {
                    "v": "Date(2020,0,23,18,30,0)"
                },
                {
                    "v": 60
                },
                {
                    "v": 65
                }
            ]
        },
        {
            "c": [
                {
                    "v": "Date(2020,0,23,19,0,0)"
                },
                {
                    "v": 77
                },
                {
                    "v": 63
                }
            ]
        },
        {
            "c": [
                {
                    "v": "Date(2020,0,23,19,30,0)"
                },
                {
                    "v": 96
                },
                {
                    "v": 71
                }
            ]
        },
        {
            "c": [
                {
                    "v": "Date(2020,0,23,20,0,0)"
                },
                {
                    "v": 54
                },
                {
                    "v": 80
                }
            ]
        },
        {
            "c": [
                {
                    "v": "Date(2020,0,23,20,30,0)"
                },
                {
                    "v": 80
                },
                {
                    "v": 94
                }
            ]
        },
        {
            "c": [
                {
                    "v": "Date(2020,0,23,21,0,0)"
                },
                {
                    "v": 92
                },
                {
                    "v": 62
                }
            ]
        },
        {
            "c": [
                {
                    "v": "Date(2020,0,23,21,30,0)"
                },
                {
                    "v": 65
                },
                {
                    "v": 53
                }
            ]
        },
        {
            "c": [
                {
                    "v": "Date(2020,0,23,22,0,0)"
                },
                {
                    "v": 60
                },
                {
                    "v": 85
                }
            ]
        },
        {
            "c": [
                {
                    "v": "Date(2020,0,23,22,30,0)"
                },
                {
                    "v": 78
                },
                {
                    "v": 73
                }
            ]
        },
        {
            "c": [
                {
                    "v": "Date(2020,0,23,23,0,0)"
                },
                {
                    "v": 86
                },
                {
                    "v": 70
                }
            ]
        },
        {
            "c": [
                {
                    "v": "Date(2020,0,23,23,30,0)"
                },
                {
                    "v": 88
                },
                {
                    "v": 75
                }
            ]
        },
        {
            "c": [
                {
                    "v": "Date(2020,0,23,24,0,0)"
                },
                {
                    "v": 78
                },
                {
                    "v": 57
                }
            ]
        }
    ]
}