{
    "cols": [
        {
            "label": "Hora",
            "type": "date"
        },
        {
            "label": "Entrantes",
            "type": "number"
        },
        {
            "label": "Salientes",
            "type": "number"
        }
    ],
    "rows": [
        {
            "c": [
                {
                    "v": "Date(2020,11,7,0,30,0)"
                },
                {
                    "v": 68
                },
                {
                    "v": 89
                }
            ]
        },
        {
            "c": [
                {
                    "v": "Date(2020,11,7,1,0,0)"
                },
                {
                    "v": 77
                },
                {
                    "v": 83
                }
            ]
        },
        {
            "c": [
                {
                    "v": "Date(2020,11,7,1,30,0)"
                },
                {
                    "v": 77
                },
                {
                    "v": 84
                }
            ]
        },
        {
            "c": [
                {
                    "v": "Date(2020,11,7,2,0,0)"
                },
                {
                    "v": 106
                },
                {
                    "v": 60
                }
            ]
        },
        {
            "c": [
                {
                    "v": "Date(2020,11,7,2,30,0)"
                },
                {
                    "v": 94
                },
                {
                    "v": 76
                }
            ]
        },
        {
            "c": [
                {
                    "v": "Date(2020,11,7,3,0,0)"
                },
                {
                    "v": 73
                },
                {
                    "v": 71
                }
            ]
        },
        {
            "c": [
                {
                    "v": "Date(2020,11,7,3,30,0)"
                },
                {
                    "v": 90
                },
                {
                    "v": 76
                }
            ]
        },
        {
            "c": [
                {
                    "v": "Date(2020,11,7,4,0,0)"
                },
                {
                    "v": 76
                },
                {
                    "v": 75
                }
            ]
        },
        {
            "c": [
                {
                    "v": "Date(2020,11,7,4,30,0)"
                },
                {
                    "v": 75
                },
                {
                    "v": 57
                }
            ]
        },
        {
            "c": [
                {
                    "v": "Date(2020,11,7,5,0,0)"
                },
                {
                    "v": 63
                },
                {
                    "v": 90
                }
            ]
        },
        {
            "c": [
                {
                    "v": "Date(2020,11,7,5,30,0)"
                },
                {
                    "v": 90
                },
                {
                    "v": 87
                }
            ]
        },
        {
            "c": [
                {
                    "v": "Date(2020,11,7,6,0,0)"
                },
                {
                    "v": 73
                },
                {
                    "v": 85
                }
            ]
        },
        {
            "c": [
                {
                    "v": "Date(2020,11,7,6,30,0)"
                },
                {
                    "v": 84
                },
                {
                    "v": 78
                }
            ]
        },
        {
            "c": [
                {
                    "v": "Date(2020,11,7,7,0,0)"
                },
                {
                    "v": 72
                },
                {
                    "v": 86
                }
            ]
        },
        {
            "c": [
                {
                    "v": "Date(2020,11,7,7,30,0)"
                },
                {
                    "v": 73
                },
                {
                    "v": 80
                }
            ]
        },
        {
            "c": [
                {
                    "v": "Date(2020,11,7,8,0,0)"
                },
                {
                    "v": 51
                },
                {
                    "v": 45
                }
            ]
        },
        {
            "c": [
                {
                    "v": "Date(2020,11,7,8,30,0)"
                },
                {
                    "v": 69
                },
                {
                    "v": 66
                }
            ]
        },
        {
            "c": [
                {
                    "v": "Date(2020,11,7,9,0,0)"
                },
                {
                    "v": 97
                },
                {
                    "v": 67
                }
            ]
        },
        {
            "c": [
                {
                    "v": "Date(2020,11,7,9,30,0)"
                },
                {
                    "v": 91
                },
                {
                    "v": 56
                }
            ]
        },
        {
            "c": [
                {
                    "v": "Date(2020,11,7,10,0,0)"
                },
                {
                    "v": 73
                },
                {
                    "v": 69
                }
            ]
        },
        {
            "c": [
                {
                    "v": "Date(2020,11,7,10,30,0)"
                },
                {
                    "v": 77
                },
                {
                    "v": 92
                }
            ]
        },
        {
            "c": [
                {
                    "v": "Date(2020,11,7,11,0,0)"
                },
                {
                    "v": 58
                },
                {
                    "v": 75
                }
            ]
        },
        {
            "c": [
                {
                    "v": "Date(2020,11,7,11,30,0)"
                },
                {
                    "v": 83
                },
                {
                    "v": 88
                }
            ]
        },
        {
            "c": [
                {
                    "v": "Date(2020,11,7,12,0,0)"
                },
                {
                    "v": 95
                },
                {
                    "v": 84
                }
            ]
        },
        {
            "c": [
                {
                    "v": "Date(2020,11,7,12,30,0)"
                },
                {
                    "v": 69
                },
                {
                    "v": 60
                }
            ]
        },
        {
            "c": [
                {
                    "v": "Date(2020,11,7,13,0,0)"
                },
                {
                    "v": 85
                },
                {
                    "v": 78
                }
            ]
        },
        {
            "c": [
                {
                    "v": "Date(2020,11,7,13,30,0)"
                },
                {
                    "v": 75
                },
                {
                    "v": 85
                }
            ]
        },
        {
            "c": [
                {
                    "v": "Date(2020,11,7,14,0,0)"
                },
                {
                    "v": 112
                },
                {
                    "v": 74
                }
            ]
        },
        {
            "c": [
                {
                    "v": "Date(2020,11,7,14,30,0)"
                },
                {
                    "v": 62
                },
                {
                    "v": 82
                }
            ]
        },
        {
            "c": [
                {
                    "v": "Date(2020,11,7,15,0,0)"
                },
                {
                    "v": 65
                },
                {
                    "v": 103
                }
            ]
        },
        {
            "c": [
                {
                    "v": "Date(2020,11,7,15,30,0)"
                },
                {
                    "v": 92
                },
                {
                    "v": 89
                }
            ]
        },
        {
            "c": [
                {
                    "v": "Date(2020,11,7,16,0,0)"
                },
                {
                    "v": 76
                },
                {
                    "v": 56
                }
            ]
        },
        {
            "c": [
                {
                    "v": "Date(2020,11,7,16,30,0)"
                },
                {
                    "v": 81
                },
                {
                    "v": 73
                }
            ]
        },
        {
            "c": [
                {
                    "v": "Date(2020,11,7,17,0,0)"
                },
                {
                    "v": 93
                },
                {
                    "v": 70
                }
            ]
        },
        {
            "c": [
                {
                    "v": "Date(2020,11,7,17,30,0)"
                },
                {
                    "v": 77
                },
                {
                    "v": 90
                }
            ]
        },
        {
            "c": [
                {
                    "v": "Date(2020,11,7,18,0,0)"
                },
                {
                    "v": 65
                },
                {
                    "v": 76
                }
            ]
        },
        {
            "c": [
                {
                    "v": "Date(2020,11,7,18,30,0)"
                },
                {
                    "v": 79
                },
                {
                    "v": 67
                }
            ]
        },
        {
            "c": [
                {
                    "v": "Date(2020,11,7,19,0,0)"
                },
                {
                    "v": 75
                },
                {
                    "v": 76
                }
            ]
        },
        {
            "c": [
                {
                    "v": "Date(2020,11,7,19,30,0)"
                },
                {
                    "v": 92
                },
                {
                    "v": 72
                }
            ]
        },
        {
            "c": [
                {
                    "v": "Date(2020,11,7,20,0,0)"
                },
                {
                    "v": 49
                },
                {
                    "v": 75
                }
            ]
        },
        {
            "c": [
                {
                    "v": "Date(2020,11,7,20,30,0)"
                },
                {
                    "v": 82
                },
                {
                    "v": 73
                }
            ]
        },
        {
            "c": [
                {
                    "v": "Date(2020,11,7,21,0,0)"
                },
                {
                    "v": 74
                },
                {
                    "v": 82
                }
            ]
        },
        {
            "c": [
                {
                    "v": "Date(2020,11,7,21,30,0)"
                },
                {
                    "v": 84
                },
                {
                    "v": 54
                }
            ]
        },
        {
            "c": [
                {
                    "v": "Date(2020,11,7,22,0,0)"
                },
                {
                    "v": 50
                },
                {
                    "v": 63
                }
            ]
        },
        {
            "c": [
                {
                    "v": "Date(2020,11,7,22,30,0)"
                },
                {
                    "v": 74
                },
                {
                    "v": 73
                }
            ]
        },
        {
            "c": [
                {
                    "v": "Date(2020,11,7,23,0,0)"
                },
                {
                    "v": 67
                },
                {
                    "v": 59
                }
            ]
        },
        {
            "c": [
                {
                    "v": "Date(2020,11,7,23,30,0)"
                },
                {
                    "v": 84
                },
                {
                    "v": 99
                }
            ]
        },
        {
            "c": [
                {
                    "v": "Date(2020,11,7,24,0,0)"
                },
                {
                    "v": 95
                },
                {
                    "v": 75
                }
            ]
        }
    ]
}